fur_validation/__init__.py
fur_validation/core.py
fur_validation/logger/__init__.py
fur_validation/logger/core.py
fur_validation/validator/__init__.py
fur_validation/validator/core.py
ptfy_fur_validation-0.0.1.dist-info/LICENSE
ptfy_fur_validation-0.0.1.dist-info/METADATA
ptfy_fur_validation-0.0.1.dist-info/WHEEL
ptfy_fur_validation-0.0.1.dist-info/top_level.txt
ptfy_fur_validation-0.0.1.dist-info/RECORD
