Metadata-Version: 2.1
Name: ptfy-fur-validation
Version: 0.0.1
Summary: A package responsible for securing the communication between systems
Home-page: https://github.com/pantherify/python-utils/tree/main/fur_validation
Author: Pantherify
Author-email: pypi@pantherify.com
License: UNKNOWN
Platform: UNKNOWN
Classifier: Programming Language :: Python :: 3
Classifier: License :: OSI Approved :: MIT License
Classifier: Operating System :: OS Independent
Requires-Python: >=3.7
License-File: LICENSE
Requires-Dist: python-dotenv
Requires-Dist: colorama
Requires-Dist: coloredlogs
